{
  "code": "200",
  "data": {
    "total":15,
    "list":[
      {
        "id":10,
        "uid":100,
        "head":"http://img.hb.aicdn.com/c3a64a5ca076113c79672d69129709f373bd7e67b20b-7Wsa4E_fw658",
        "name":"张小宾",
        "desc":"心理学博士，我的特长是心理学博士，我的特长是心理学博士，我的特长是心理学博士，我的特长是",
        "tags":"个人成长,家庭，家庭2",
        "listenNums":0,
        "status":1
      },
      {
        "id":11,
        "uid":100,
        "head":"http://img.hb.aicdn.com/c3a64a5ca076113c79672d69129709f373bd7e67b20b-7Wsa4E_fw658",
        "name":"2张小宾",
        "desc":"心理学博士，我的特长是心理学博士，我的特长是心理学博士，我的特长是心理学博士，我的特长是",
        "tags":"个人成长,家庭，家庭2,家庭3,家庭4",
        "listenNums":20,
        "status":2
      }
    ]
  },
  "msg": "成功"
}
